logki/__init__.py
logki/app.py
logki/logic.py
logki/utils.py
logki-1.0.3.dist-info/AUTHORS.rst
logki-1.0.3.dist-info/LICENSE
logki-1.0.3.dist-info/METADATA
logki-1.0.3.dist-info/WHEEL
logki-1.0.3.dist-info/entry_points.txt
logki-1.0.3.dist-info/top_level.txt
logki-1.0.3.dist-info/RECORD
