Metadata-Version: 2.1
Name: logki
Version: 1.0.3
Summary: logki: Log Analysis Kit
Author-email: Tomas Fiedor <TomasFiedor@gmail.com>
License: GNU GENERAL PUBLIC LICENSE
Project-URL: Repository, https://github.com/Perfexionists/logki.git
Project-URL: Changelog, https://github.com/Perfexionists/logki/blob/master/CHANGELOG.rst
Requires-Python: >=3.9
License-File: LICENSE
License-File: AUTHORS.rst
Requires-Dist: prompt-toolkit >=3.0.43
Requires-Dist: tabulate >=0.9
Provides-Extra: docs
Requires-Dist: Sphinx >=7.1 ; extra == 'docs'
Requires-Dist: sphinx-click >=5.0 ; extra == 'docs'
Provides-Extra: lint
Requires-Dist: black >=22.1.0 ; extra == 'lint'
Requires-Dist: pylint >=2.17 ; extra == 'lint'
Provides-Extra: test
Requires-Dist: pytest >=7.4 ; extra == 'test'
Requires-Dist: pytest-cov >=4.1 ; extra == 'test'
Requires-Dist: tox >=4.9.0 ; extra == 'test'
Provides-Extra: typing
Requires-Dist: mypy >=1.5 ; extra == 'typing'
Requires-Dist: mypy-extensions >=1.0 ; extra == 'typing'
Requires-Dist: typing-extensions >=4.7 ; extra == 'typing'
Requires-Dist: types-tabulate >=0.9 ; extra == 'typing'
